Workbook

Sheet _README
A1: Master Dataset ของโครงงาน NutriPlan (งานที่ 4 DADD)
A3: โครงสร้าง: 12 ชีตข้อมูล ชื่อชีตตรงกับชื่อ Node ใน Firebase และชื่อคอลัมน์ตรงกับพจนานุกรมข้อมูลในรายงานหัวข้อ 3
A4: ข้อมูลอ้างอิง (Lookup): categories, vendor_types, activity_levels, health_goals, nutrient_limits
A5: ข้อมูลหลัก (Master): menus, articles, menu_images, sources, users
A6: ข้อมูลธุรกรรม (Transaction): user_targets, meal_logs
A7: ชีต _summary คำนวณตัวชี้วัดด้วยสูตร จึงอัปเดตอัตโนมัติเมื่อแก้ไขข้อมูล
A8: ชีต user_targets เป็นสูตรทั้งหมด (ยกเว้น calculated_at) คำนวณจากชีต users
A10: หลักการบันทึกข้อมูล
A11: • รหัสข้อมูลตัวพิมพ์เล็ก ใช้เป็นคีย์ JSON ได้ทันที (ไม่มี . $ # [ ] /)
A12: • ข้อมูลหลายค่าในเซลล์เดียว (tags, source_ids) คั่นด้วย | ส่วน key_points คั่นด้วย " | "
A13: • วันที่ใช้ ISO 8601 (YYYY-MM-DD) ยกเว้น birth_year เป็นปี พ.ศ.
A14: • คอลัมน์ที่มีค่ามาตรฐานตั้ง Data Validation ไว้ เช่น category_id, verification_status, meal_type, role
... A25: • ค่าโภชนาการเป็นค่าประมาณต่อจาน ที่มาของค่ารายเมนูจะบันทึกระหว่างขั้นสอบทาน

Sheet _summary
A1: ตัวชี้วัด | B1: ค่า | C1: สูตร/หมายเหตุ
A2: จำนวนแถว categories | B2: =COUNTA(categories!A:A)-1 -> 8 | C2: COUNTA ของคอลัมน์รหัส
A3: จำนวนแถว vendor_types | B3: =COUNTA(vendor_types!A:A)-1 -> 7 | C3: COUNTA ของคอลัมน์รหัส
A4: จำนวนแถว activity_levels | B4: =COUNTA(activity_levels!A:A)-1 -> 5 | C4: COUNTA ของคอลัมน์รหัส
A5: จำนวนแถว health_goals | B5: =COUNTA(health_goals!A:A)-1 -> 3 | C5: COUNTA ของคอลัมน์รหัส
A6: จำนวนแถว nutrient_limits | B6: =COUNTA(nutrient_limits!A:A)-1 -> 7 | C6: COUNTA ของคอลัมน์รหัส
A7: จำนวนแถว menus | B7: =COUNTA(menus!A:A)-1 -> 49 | C7: COUNTA ของคอลัมน์รหัส
A8: จำนวนแถว articles | B8: =COUNTA(articles!A:A)-1 -> 12 | C8: COUNTA ของคอลัมน์รหัส
A9: จำนวนแถว menu_images | B9: =COUNTA(menu_images!A:A)-1 -> 61 | C9: COUNTA ของคอลัมน์รหัส
A10: จำนวนแถว sources | B10: =COUNTA(sources!A:A)-1 -> 17 | C10: COUNTA ของคอลัมน์รหัส
A11: จำนวนแถว users | B11: =COUNTA(users!A:A)-1 -> 25 | C11: COUNTA ของคอลัมน์รหัส
A12: จำนวนแถว user_targets | B12: =COUNTA(user_targets!A:A)-1 -> 25 | C12: COUNTA ของคอลัมน์รหัส
A13: จำนวนแถว meal_logs | B13: =COUNTA(meal_logs!A:A)-1 -> 1108 | C13: COUNTA ของคอลัมน์รหัส
A14: รวมทุกชีต | B14: =SUM(B2:B13) -> 1327
A15: เมนูที่ยัง PENDING | B15: =COUNTIF(menus!V:V,"PENDING") -> 49
A16: ภาพเมนูสถานะ DONE | B16: =COUNTIFS(menu_images!C:C,"menu",menu_images!H:H,"DONE") -> 49
A17: ภาพปกบทความสถานะ TODO | B17: =COUNTIFS(menu_images!C:C,"article_cover",menu_images!H:H,"TODO") -> 12
A18: จำนวนวัน-ผู้ใช้ที่มีการบันทึก (ดูชีต meal_logs) | B18: =SUMPRODUCT((meal_logs!B2:B1109&meal_logs!C2:C1109<>"")/COUNTIFS(meal_logs!B2:B1109,meal_logs!B2:B1109,meal_logs!C2:C1109,meal_logs!C2:C1109)) -> 304 | C18: คู่ user_id + log_date ที่ไม่ซ้ำ
A20: หมวดอาหาร | B20: จำนวนเมนู | C20: พลังงานเฉลี่ย (kcal) | D20: โซเดียมเฉลี่ย (มก.)
A21: =categories!A2 -> cat_rice | B21: =COUNTIF(menus!$D$2:$D$50,A21) -> 6 | C21: =ROUND(AVERAGEIF(menus!$D$2:$D$50,A21,menus!$I$2:$I$50),0) -> 628 | D21: =ROUND(AVERAGEIF(menus!$D$2:$D$50,A21,menus!$O$2:$O$50),0) -> 1325
A22: =categories!A3 -> cat_stir | B22: =COUNTIF(menus!$D$2:$D$50,A22) -> 9 | C22: =ROUND(AVERAGEIF(menus!$D$2:$D$50,A22,menus!$I$2:$I$50),0) -> 638 | D22: =ROUND(AVERAGEIF(menus!$D$2:$D$50,A22,menus!$O$2:$O$50),0) -> 1450
A23: =categories!A4 -> cat_noodle | B23: =COUNTIF(menus!$D$2:$D$50,A23) -> 12 | C23: =ROUND(AVERAGEIF(menus!$D$2:$D$50,A23,menus!$I$2:$I$50),0) -> 500 | D23: =ROUND(AVERAGEIF(menus!$D$2:$D$50,A23,menus!$O$2:$O$50),0) -> 1679
A24: =categories!A5 -> cat_isaan | B24: =COUNTIF(menus!$D$2:$D$50,A24) -> 6 | C24: =ROUND(AVERAGEIF(menus!$D$2:$D$50,A24,menus!$I$2:$I$50),0) -> 273 | D24: =ROUND(AVERAGEIF(menus!$D$2:$D$50,A24,menus!$O$2:$O$50),0) -> 1142
A25: =categories!A6 -> cat_curry | B25: =COUNTIF(menus!$D$2:$D$50,A25) -> 7 | C25: =ROUND(AVERAGEIF(menus!$D$2:$D$50,A25,menus!$I$2:$I$50),0) -> 321 | D25: =ROUND(AVERAGEIF(menus!$D$2:$D$50,A25,menus!$O$2:$O$50),0) -> 1357
A26: =categories!A7 -> cat_drink | B26: =COUNTIF(menus!$D$2:$D$50,A26) -> 5 | C26: =ROUND(AVERAGEIF(menus!$D$2:$D$50,A26,menus!$I$2:$I$50),0) -> 162 | D26: =ROUND(AVERAGEIF(menus!$D$2:$D$50,A26,menus!$O$2:$O$50),0) -> 62
A27: =categories!A8 -> cat_dessert | B27: =COUNTIF(menus!$D$2:$D$50,A27) -> 2 | C27: =ROUND(AVERAGEIF(menus!$D$2:$D$50,A27,menus!$I$2:$I$50),0) -> 285 | D27: =ROUND(AVERAGEIF(menus!$D$2:$D$50,A27,menus!$O$2:$O$50),0) -> 93
A28: =categories!A9 -> cat_side | B28: =COUNTIF(menus!$D$2:$D$50,A28) -> 2 | C28: =ROUND(AVERAGEIF(menus!$D$2:$D$50,A28,menus!$I$2:$I$50),0) -> 209 | D28: =ROUND(AVERAGEIF(menus!$D$2:$D$50,A28,menus!$O$2:$O$50),0) -> 4
A29: รวม / เฉลี่ยทั้งหมด | B29: =SUM(B21:B28) -> 49 | C29: =ROUND(AVERAGE(menus!I2:I50),0) -> 432 | D29: =ROUND(AVERAGE(menus!O2:O50),0) -> 1184

Sheet categories
A1: category_id | B1: name_th | C1: name_en | D1: description | E1: icon_file | F1: color_hex | G1: sort_order
A2: cat_rice | B2: ข้าวจานเดียว | C2: Rice Dishes | D2: ข้าวราดหน้าหรือข้าวพร้อมกับข้าวในจานเดียว | E2: icon_cat_rice.svg | F2: #C2410C | G2: 1
A3: cat_stir | B3: ข้าวผัด/ตามสั่ง | C3: Stir-fried Dishes | D3: อาหารผัดสั่งทำสดราดข้าว | E3: icon_cat_stir.svg | F3: #B45309 | G3: 2
A4: cat_noodle | B4: ก๋วยเตี๋ยวและเส้น | C4: Noodle Dishes | D4: อาหารประเภทเส้นทั้งน้ำและแห้ง | E4: icon_cat_noodle.svg | F4: #0F766E | G4: 3
A5: cat_isaan | B5: อาหารอีสาน | C5: Isan Food | D5: ส้มตำ ลาบ ย่าง และอาหารอีสานทั่วไป | E5: icon_cat_isaan.svg | F5: #15803D | G5: 4
A6: cat_curry | B6: แกงและกับข้าว | C6: Curry and Side Dish | D6: แกง ต้ม ผัดผัก ที่สั่งเป็นกับข้าว | E6: icon_cat_curry.svg | F6: #A16207 | G6: 5
A7: cat_drink | B7: เครื่องดื่ม | C7: Beverages | D7: เครื่องดื่มที่สั่งคู่กับมื้ออาหาร | E7: icon_cat_drink.svg | F7: #1D4ED8 | G7: 6
A8: cat_dessert | B8: ของหวานและผลไม้ | C8: Dessert and Fruit | D8: ของหวานและผลไม้ที่รับประทานหลังมื้ออาหาร | E8: icon_cat_dessert.svg | F8: #BE185D | G8: 7
A9: cat_side | B9: ข้าวและเครื่องเคียง | C9: Staple and Side | D9: ข้าวสวย ข้าวเหนียว และเครื่องเคียงแยกจาน | E9: icon_cat_side.svg | F9: #4D7C0F | G9: 8

Sheet vendor_types
A1: vendor_type_id | B1: name_th | C1: name_en
A2: shop_tamsang | B2: ร้านอาหารตามสั่ง | C2: Made-to-order Shop
A3: shop_rice | B3: ร้านข้าวจานเดียว | C3: Single-dish Rice Shop
A4: shop_noodle | B4: ร้านก๋วยเตี๋ยว | C4: Noodle Shop
A5: shop_isaan | B5: ร้านส้มตำ/อาหารอีสาน | C5: Isan Food Shop
A6: shop_curry | B6: ร้านข้าวราดแกง | C6: Curry-over-rice Shop
A7: shop_drink | B7: ร้านเครื่องดื่ม | C7: Beverage Stall
A8: shop_dessert | B8: ร้านของหวาน/ผลไม้ | C8: Dessert and Fruit Stall

Sheet activity_levels
A1: activity_id | B1: name_th | C1: pal_factor | D1: example | E1: sort_order
A2: act_sedentary | B2: นั่งทำงานเป็นหลัก ไม่ออกกำลังกาย | C2: 1.2 | D2: นั่งเรียนหรือนั่งทำงานเกือบทั้งวัน | E2: 1
A3: act_light | B3: ออกกำลังกายเบา 1-3 วันต่อสัปดาห์ | C3: 1.375 | D3: เดินระหว่างตึกเรียน ออกกำลังกายเบาบ้าง | E3: 2
A4: act_moderate | B4: ออกกำลังกายปานกลาง 3-5 วันต่อสัปดาห์ | C4: 1.55 | D4: ออกกำลังกายสม่ำเสมอหรือทำงานที่ต้องยืนเดิน | E4: 3
A5: act_active | B5: ออกกำลังกายหนัก 6-7 วันต่อสัปดาห์ | C5: 1.725 | D5: เล่นกีฬาหรือเข้ายิมเกือบทุกวัน | E5: 4
A6: act_very | B6: ออกกำลังกายหนักมากหรือใช้แรงงาน | C6: 1.9 | D6: นักกีฬาหรือผู้ใช้แรงงานหนัก | E6: 5

Sheet health_goals
A1: goal_id | B1: name_th | C1: kcal_adjust | D1: description | E1: sort_order
A2: goal_lose | B2: ลดน้ำหนัก | C2: -500 | D2: ลดพลังงานจาก TDEE วันละ 500 กิโลแคลอรี | E2: 1
A3: goal_maintain | B3: คงน้ำหนัก | C3: 0 | D3: รับพลังงานเท่ากับ TDEE | E3: 2
A4: goal_gain | B4: เพิ่มน้ำหนัก | C4: 300 | D4: เพิ่มพลังงานจาก TDEE วันละ 300 กิโลแคลอรี | E4: 3

Sheet nutrient_limits
A1: nutrient_key | B1: name_th | C1: name_en | D1: unit | E1: limit_type | F1: limit_value | G1: source_id | H1: article_id | I1: sort_order
A2: energy_kcal | B2: พลังงาน | C2: Energy | D2: kcal | E2: personal | F2: 0 | G2: src_05 | H2: article_01 | I2: 1
A3: protein_g | B3: โปรตีน | C3: Protein | D3: g | E3: per_kg | F3: 1 | G3: src_02 | H3: article_05 | I3: 2
A4: fat_g | B4: ไขมัน | C4: Fat | D4: g | E4: info | F4: 0 | G4: src_02 | H4: article_09 | I4: 3
A5: carb_g | B5: คาร์โบไฮเดรต | C5: Carbohydrate | D5: g | E5: info | F5: 0 | G5: src_02 | H5: article_07 | I5: 4
A6: sugar_g | B6: น้ำตาล | C6: Sugar | D6: g | E6: max | F6: 50 | G6: src_04 | H6: article_04 | I6: 5
A7: fiber_g | B7: ใยอาหาร | C7: Dietary Fiber | D7: g | E7: min | F7: 25 | G7: src_02 | H7: article_06 | I7: 6
A8: sodium_mg | B8: โซเดียม | C8: Sodium | D8: mg | E8: max | F8: 2000 | G8: src_03 | H8: article_03 | I8: 7

Sheet menus
A1: menu_id | B1: name_th | C1: name_en | D1: category_id | E1: vendor_type_id | F1: serving_desc | G1: serving_g | H1: price_thb | I1: energy_kcal | J1: protein_g | K1: fat_g | L1: carb_g | M1: sugar_g | N1: fiber_g | O1: sodium_mg | P1: is_vegetarian | Q1: spicy_level | R1: tags | S1: image_thumb | T1: image_detail | U1: source_id | V1: verification_status | W1: updated_at
A2: menu_001 | B2: ข้าวมันไก่ | C2: Hainanese Chicken Rice | D2: cat_rice | E2: shop_rice | F2: 1 จาน | G2: 350 | H2: 50 | I2: 596 | J2: 28 | K2: 22 | L2: 70 | M2: 3 | N2: 2 | O2: 1100 | P2: =FALSE() -> FALSE | Q2: 0 | R2: ไก่|ข้าว|มื้อกลางวัน | S2: images/menus/menu_001_thumb.webp | T2: images/menus/menu_001_detail.webp | U2: src_01 | V2: PENDING | W2: 2026-09-20
A3: menu_002 | B3: ข้าวหมูแดง | C3: Red Pork with Rice | D3: cat_rice | E3: shop_rice | F3: 1 จาน | G3: 330 | H3: 50 | I3: 560 | J3: 25 | K3: 16 | L3: 78 | M3: 12 | N3: 2 | O3: 1200 | P3: =FALSE() -> FALSE | Q3: 0 | R3: หมู|ข้าว | S3: images/menus/menu_002_thumb.webp | T3: images/menus/menu_002_detail.webp | U3: src_01 | V3: PENDING | W3: 2026-09-20
A4: menu_003 | B4: ข้าวขาหมู | C4: Stewed Pork Leg with Rice | D4: cat_rice | E4: shop_rice | F4: 1 จาน | G4: 380 | H4: 55 | I4: 680 | J4: 30 | K4: 28 | L4: 75 | M4: 8 | N4: 3 | O4: 1500 | P4: =FALSE() -> FALSE | Q4: 0 | R4: หมู|ข้าว|ไขมันสูง | S4: images/menus/menu_003_thumb.webp | T4: images/menus/menu_003_detail.webp | U4: src_01 | V4: PENDING | W4: 2026-09-20
A5: menu_004 | B5: ข้าวหน้าเป็ด | C5: Roasted Duck with Rice | D5: cat_rice | E5: shop_rice | F5: 1 จาน | G5: 350 | H5: 60 | I5: 620 | J5: 32 | K5: 20 | L5: 75 | M5: 6 | N5: 2 | O5: 1300 | P5: =FALSE() -> FALSE | Q5: 0 | R5: เป็ด|ข้าว|โปรตีนสูง | S5: images/menus/menu_004_thumb.webp | T5: images/menus/menu_004_detail.webp | U5: src_01 | V5: PENDING | W5: 2026-09-20
A6: menu_005 | B6: ข้าวคลุกกะปิ | C6: Shrimp Paste Fried Rice | D6: cat_rice | E6: shop_tamsang | F6: 1 จาน | G6: 320 | H6: 50 | I6: 610 | J6: 20 | K6: 22 | L6: 82 | M6: 14 | N6: 3 | O6: 1600 | P6: =FALSE() -> FALSE | Q6: 1 | R6: กุ้ง|ข้าว|โซเดียมสูง | S6: images/menus/menu_005_thumb.webp | T6: images/menus/menu_005_detail.webp | U6: src_01 | V6: PENDING | W6: 2026-09-20
A7: menu_006 | B7: ข้าวหมูกรอบ | C7: Crispy Pork with Rice | D7: cat_rice | E7: shop_rice | F7: 1 จาน | G7: 330 | H7: 55 | I7: 700 | J7: 24 | K7: 34 | L7: 72 | M7: 4 | N7: 2 | O7: 1250 | P7: =FALSE() -> FALSE | Q7: 0 | R7: หมู|ข้าว|ไขมันสูง | S7: images/menus/menu_006_thumb.webp | T7: images/menus/menu_006_detail.webp | U7: src_01 | V7: PENDING | W7: 2026-09-20
A8: menu_007 | B8: ข้าวผัดกะเพราหมูสับไข่ดาว | C8: Stir-fried Basil Pork with Rice and Fried Egg | D8: cat_stir | E8: shop_tamsang | F8: 1 จาน | G8: 380 | H8: 55 | I8: 680 | J8: 30 | K8: 32 | L8: 68 | M8: 5 | N8: 3 | O8: 1700 | P8: =FALSE() -> FALSE | Q8: 2 | R8: หมู|ไข่|เผ็ด|โซเดียมสูง | S8: images/menus/menu_007_thumb.webp | T8: images/menus/menu_007_detail.webp | U8: src_01 | V8: PENDING | W8: 2026-09-20
A9: menu_008 | B9: ข้าวผัดกะเพราไก่ | C9: Stir-fried Basil Chicken with Rice | D9: cat_stir | E9: shop_tamsang | F9: 1 จาน | G9: 350 | H9: 50 | I9: 580 | J9: 28 | K9: 20 | L9: 68 | M9: 5 | N9: 3 | O9: 1500 | P9: =FALSE() -> FALSE | Q9: 2 | R9: ไก่|เผ็ด | S9: images/menus/menu_008_thumb.webp | T9: images/menus/menu_008_detail.webp | U9: src_01 | V9: PENDING | W9: 2026-09-20
A10: menu_009 | B10: ข้าวผัดหมู | C10: Pork Fried Rice | D10: cat_stir | E10: shop_tamsang | F10: 1 จาน | G10: 350 | H10: 50 | I10: 560 | J10: 22 | K10: 18 | L10: 75 | M10: 4 | N10: 2 | O10: 1200 | P10: =FALSE() -> FALSE | Q10: 0 | R10: หมู|ข้าวผัด | S10: images/menus/menu_009_thumb.webp | T10: images/menus/menu_009_detail.webp | U10: src_01 | V10: PENDING | W10: 2026-09-20
A11: menu_010 | B11: ข้าวผัดอเมริกัน | C11: American Fried Rice | D11: cat_stir | E11: shop_tamsang | F11: 1 จาน | G11: 400 | H11: 70 | I11: 850 | J11: 28 | K11: 38 | L11: 95 | M11: 12 | N11: 3 | O11: 1900 | P11: =FALSE() -> FALSE | Q11: 0 | R11: ไส้กรอก|ไข่|พลังงานสูง | S11: images/menus/menu_010_thumb.webp | T11: images/menus/menu_010_detail.webp | U11: src_01 | V11: PENDING | W11: 2026-09-20
A12: menu_011 | B12: ข้าวผัดพริกแกงหมู | C12: Stir-fried Red Curry Paste with Pork and Rice | D12: cat_stir | E12: shop_tamsang | F12: 1 จาน | G12: 350 | H12: 55 | I12: 620 | J12: 24 | K12: 26 | L12: 70 | M12: 6 | N12: 4 | O12: 1500 | P12: =FALSE() -> FALSE | Q12: 2 | R12: หมู|เผ็ด | S12: images/menus/menu_011_thumb.webp | T12: images/menus/menu_011_detail.webp | U12: src_01 | V12: PENDING | W12: 2026-09-20
A13: menu_012 | B13: ข้าวผัดกระเทียมหมู | C13: Garlic Pork with Rice | D13: cat_stir | E13: shop_tamsang | F13: 1 จาน | G13: 340 | H13: 50 | I13: 590 | J13: 26 | K13: 22 | L13: 70 | M13: 3 | N13: 2 | O13: 1300 | P13: =FALSE() -> FALSE | Q13: 0 | R13: หมู|กระเทียม | S13: images/menus/menu_012_thumb.webp | T13: images/menus/menu_012_detail.webp | U13: src_01 | V13: PENDING | W13: 2026-09-20
... A28: menu_027 | B28: สุกี้แห้งหมู | C28: Dry Suki with Pork | D28: cat_noodle | E28: shop_tamsang | F28: 1 จาน | G28: 350 | H28: 55 | I28: 520 | J28: 24 | K28: 20 | L28: 58 | M28: 12 | N28: 4 | O28: 1700 | P28: =FALSE() -> FALSE | Q28: 1 | R28: หมู|ผัก | S28: images/menus/menu_027_thumb.webp | T28: images/menus/menu_027_detail.webp | U28: src_01 | V28: PENDING | W28: 2026-09-20
A29: menu_028 | B29: ส้มตำไทย | C29: Thai Green Papaya Salad | D29: cat_isaan | E29: shop_isaan | F29: 1 จาน | G29: 200 | H29: 40 | I29: 135 | J29: 4 | K29: 3 | L29: 24 | M29: 14 | N29: 5 | O29: 900 | P29: =TRUE() -> TRUE | Q29: 2 | R29: มังสวิรัติได้|ผัก|เผ็ด | S29: images/menus/menu_028_thumb.webp | T29: images/menus/menu_028_detail.webp | U29: src_01 | V29: PENDING | W29: 2026-09-20
A30: menu_029 | B30: ส้มตำปูปลาร้า | C30: Papaya Salad with Crab and Fermented Fish | D30: cat_isaan | E30: shop_isaan | F30: 1 จาน | G30: 220 | H30: 45 | I30: 150 | J30: 8 | K30: 3 | L30: 22 | M30: 10 | N30: 5 | O30: 1500 | P30: =FALSE() -> FALSE | Q30: 3 | R30: ปู|เผ็ด|โซเดียมสูง | S30: images/menus/menu_029_thumb.webp | T30: images/menus/menu_029_detail.webp | U30: src_01 | V30: PENDING | W30: 2026-09-20
A31: menu_030 | B31: ลาบหมู | C31: Spicy Minced Pork Salad | D31: cat_isaan | E31: shop_isaan | F31: 1 จาน | G31: 150 | H31: 50 | I31: 230 | J31: 20 | K31: 14 | L31: 6 | M31: 2 | N31: 2 | O31: 1100 | P31: =FALSE() -> FALSE | Q31: 3 | R31: หมู|เผ็ด|โปรตีนสูง | S31: images/menus/menu_030_thumb.webp | T31: images/menus/menu_030_detail.webp | U31: src_01 | V31: PENDING | W31: 2026-09-20
A32: menu_031 | B32: ไก่ย่าง (หนึ่งในสี่ตัว) | C32: Grilled Chicken (Quarter) | D32: cat_isaan | E32: shop_isaan | F32: 1 ชิ้น | G32: 180 | H32: 60 | I32: 380 | J32: 34 | K32: 24 | L32: 4 | M32: 2 | N32: 0 | O32: 800 | P32: =FALSE() -> FALSE | Q32: 0 | R32: ไก่|โปรตีนสูง | S32: images/menus/menu_031_thumb.webp | T32: images/menus/menu_031_detail.webp | U32: src_01 | V32: PENDING | W32: 2026-09-20
A33: menu_032 | B33: คอหมูย่าง | C33: Grilled Pork Neck | D33: cat_isaan | E33: shop_isaan | F33: 1 จาน | G33: 150 | H33: 60 | I33: 420 | J33: 26 | K33: 34 | L33: 3 | M33: 2 | N33: 0 | O33: 750 | P33: =FALSE() -> FALSE | Q33: 0 | R33: หมู|ไขมันสูง | S33: images/menus/menu_032_thumb.webp | T33: images/menus/menu_032_detail.webp | U33: src_01 | V33: PENDING | W33: 2026-09-20
A34: menu_033 | B34: ข้าวเหนียว | C34: Sticky Rice | D34: cat_side | E34: shop_isaan | F34: 1 ห่อ | G34: 120 | H34: 10 | I34: 210 | J34: 4 | K34: 0.5 | L34: 46 | M34: 0 | N34: 1 | O34: 5 | P34: =TRUE() -> TRUE | Q34: 0 | R34: ข้าว|เครื่องเคียง | S34: images/menus/menu_033_thumb.webp | T34: images/menus/menu_033_detail.webp | U34: src_01 | V34: PENDING | W34: 2026-09-20
A35: menu_034 | B35: ต้มแซ่บกระดูกหมู | C35: Spicy Pork Rib Soup | D35: cat_isaan | E35: shop_isaan | F35: 1 ถ้วย | G35: 400 | H35: 60 | I35: 320 | J35: 24 | K35: 18 | L35: 12 | M35: 4 | N35: 2 | O35: 1800 | P35: =FALSE() -> FALSE | Q35: 3 | R35: หมู|เผ็ด|โซเดียมสูง | S35: images/menus/menu_034_thumb.webp | T35: images/menus/menu_034_detail.webp | U35: src_01 | V35: PENDING | W35: 2026-09-20
A36: menu_035 | B36: แกงเขียวหวานไก่ราดข้าว | C36: Green Curry Chicken with Rice | D36: cat_curry | E36: shop_curry | F36: 1 จาน | G36: 400 | H36: 50 | I36: 600 | J36: 24 | K36: 30 | L36: 60 | M36: 8 | N36: 4 | O36: 1500 | P36: =FALSE() -> FALSE | Q36: 2 | R36: ไก่|กะทิ | S36: images/menus/menu_035_thumb.webp | T36: images/menus/menu_035_detail.webp | U36: src_01 | V36: PENDING | W36: 2026-09-20
A37: menu_036 | B37: แกงจืดเต้าหู้หมูสับ | C37: Clear Soup with Tofu and Minced Pork | D37: cat_curry | E37: shop_curry | F37: 1 ถ้วย | G37: 350 | H37: 45 | I37: 180 | J37: 16 | K37: 9 | L37: 10 | M37: 3 | N37: 2 | O37: 1200 | P37: =FALSE() -> FALSE | Q37: 0 | R37: หมู|เต้าหู้|พลังงานต่ำ | S37: images/menus/menu_036_thumb.webp | T37: images/menus/menu_036_detail.webp | U37: src_01 | V37: PENDING | W37: 2026-09-20
A38: menu_037 | B38: ต้มยำกุ้งน้ำข้น | C38: Creamy Tom Yum Goong | D38: cat_curry | E38: shop_tamsang | F38: 1 ถ้วย | G38: 350 | H38: 80 | I38: 300 | J38: 22 | K38: 18 | L38: 14 | M38: 6 | N38: 2 | O38: 1900 | P38: =FALSE() -> FALSE | Q38: 3 | R38: กุ้ง|เผ็ด|โซเดียมสูง | S38: images/menus/menu_037_thumb.webp | T38: images/menus/menu_037_detail.webp | U38: src_01 | V38: PENDING | W38: 2026-09-20
A39: menu_038 | B39: แกงส้มผักรวมกุ้ง | C39: Sour Curry with Mixed Vegetables and Shrimp | D39: cat_curry | E39: shop_curry | F39: 1 ถ้วย | G39: 350 | H39: 55 | I39: 220 | J39: 18 | K39: 5 | L39: 25 | M39: 10 | N39: 5 | O39: 1600 | P39: =FALSE() -> FALSE | Q39: 2 | R39: กุ้ง|ผัก | S39: images/menus/menu_038_thumb.webp | T39: images/menus/menu_038_detail.webp | U39: src_01 | V39: PENDING | W39: 2026-09-20
A40: menu_039 | B40: พะแนงหมูราดข้าว | C40: Panang Curry Pork with Rice | D40: cat_curry | E40: shop_curry | F40: 1 จาน | G40: 380 | H40: 55 | I40: 640 | J40: 26 | K40: 32 | L40: 62 | M40: 10 | N40: 3 | O40: 1450 | P40: =FALSE() -> FALSE | Q40: 1 | R40: หมู|กะทิ | S40: images/menus/menu_039_thumb.webp | T40: images/menus/menu_039_detail.webp | U40: src_01 | V40: PENDING | W40: 2026-09-20
A41: menu_040 | B41: ผัดผักรวมมิตร | C41: Stir-fried Mixed Vegetables | D41: cat_curry | E41: shop_tamsang | F41: 1 จาน | G41: 200 | H41: 40 | I41: 160 | J41: 6 | K41: 10 | L41: 14 | M41: 5 | N41: 5 | O41: 900 | P41: =TRUE() -> TRUE | Q41: 0 | R41: ผัก|มังสวิรัติได้ | S41: images/menus/menu_040_thumb.webp | T41: images/menus/menu_040_detail.webp | U41: src_01 | V41: PENDING | W41: 2026-09-20
A42: menu_041 | B42: ผัดผักบุ้งไฟแดง | C42: Stir-fried Morning Glory | D42: cat_curry | E42: shop_tamsang | F42: 1 จาน | G42: 180 | H42: 40 | I42: 150 | J42: 5 | K42: 10 | L42: 12 | M42: 4 | N42: 4 | O42: 950 | P42: =TRUE() -> TRUE | Q42: 1 | R42: ผัก|มังสวิรัติได้ | S42: images/menus/menu_041_thumb.webp | T42: images/menus/menu_041_detail.webp | U42: src_01 | V42: PENDING | W42: 2026-09-20
A43: menu_042 | B43: ชาไทยเย็น | C43: Thai Iced Milk Tea | D43: cat_drink | E43: shop_drink | F43: 1 แก้ว | G43: 350 | H43: 30 | I43: 280 | J43: 4 | K43: 8 | L43: 48 | M43: 44 | N43: 0 | O43: 100 | P43: =TRUE() -> TRUE | Q43: 0 | R43: น้ำตาลสูง | S43: images/menus/menu_042_thumb.webp | T43: images/menus/menu_042_detail.webp | U43: src_01 | V43: PENDING | W43: 2026-09-20
A44: menu_043 | B44: กาแฟเย็น | C44: Thai Iced Coffee | D44: cat_drink | E44: shop_drink | F44: 1 แก้ว | G44: 350 | H44: 35 | I44: 250 | J44: 3 | K44: 7 | L44: 44 | M44: 40 | N44: 0 | O44: 80 | P44: =TRUE() -> TRUE | Q44: 0 | R44: น้ำตาลสูง|คาเฟอีน | S44: images/menus/menu_043_thumb.webp | T44: images/menus/menu_043_detail.webp | U44: src_01 | V44: PENDING | W44: 2026-09-20
A45: menu_044 | B45: โอเลี้ยง | C45: Thai Iced Black Coffee | D45: cat_drink | E45: shop_drink | F45: 1 แก้ว | G45: 350 | H45: 25 | I45: 160 | J45: 0 | K45: 0 | L45: 40 | M45: 38 | N45: 0 | O45: 40 | P45: =TRUE() -> TRUE | Q45: 0 | R45: น้ำตาลสูง|คาเฟอีน | S45: images/menus/menu_044_thumb.webp | T45: images/menus/menu_044_detail.webp | U45: src_01 | V45: PENDING | W45: 2026-09-20
A46: menu_045 | B46: น้ำเปล่า | C46: Drinking Water | D46: cat_drink | E46: shop_drink | F46: 1 ขวด | G46: 500 | H46: 10 | I46: 0 | J46: 0 | K46: 0 | L46: 0 | M46: 0 | N46: 0 | O46: 2 | P46: =TRUE() -> TRUE | Q46: 0 | R46: ไม่มีพลังงาน | S46: images/menus/menu_045_thumb.webp | T46: images/menus/menu_045_detail.webp | U46: src_01 | V46: PENDING | W46: 2026-09-20
A47: menu_046 | B47: นมถั่วเหลืองหวานน้อย | C47: Low-sugar Soy Milk | D47: cat_drink | E47: shop_drink | F47: 1 ขวด | G47: 300 | H47: 20 | I47: 120 | J47: 7 | K47: 4 | L47: 15 | M47: 9 | N47: 1 | O47: 90 | P47: =TRUE() -> TRUE | Q47: 0 | R47: โปรตีนพืช|มังสวิรัติได้ | S47: images/menus/menu_046_thumb.webp | T47: images/menus/menu_046_detail.webp | U47: src_01 | V47: PENDING | W47: 2026-09-20
A48: menu_047 | B48: ข้าวเหนียวมะม่วง | C48: Mango with Sticky Rice | D48: cat_dessert | E48: shop_dessert | F48: 1 จาน | G48: 250 | H48: 60 | I48: 480 | J48: 6 | K48: 16 | L48: 78 | M48: 48 | N48: 3 | O48: 180 | P48: =TRUE() -> TRUE | Q48: 0 | R48: ของหวาน|น้ำตาลสูง | S48: images/menus/menu_047_thumb.webp | T48: images/menus/menu_047_detail.webp | U48: src_01 | V48: PENDING | W48: 2026-09-20
A49: menu_048 | B49: ผลไม้รวม (ฝรั่งและสับปะรด) | C49: Mixed Fruit (Guava and Pineapple) | D49: cat_dessert | E49: shop_dessert | F49: 1 กล่อง | G49: 200 | H49: 25 | I49: 90 | J49: 1 | K49: 0.3 | L49: 22 | M49: 18 | N49: 4 | O49: 5 | P49: =TRUE() -> TRUE | Q49: 0 | R49: ผลไม้|ใยอาหารสูง | S49: images/menus/menu_048_thumb.webp | T49: images/menus/menu_048_detail.webp | U49: src_01 | V49: PENDING | W49: 2026-09-20
A50: menu_049 | B50: ข้าวสวย | C50: Steamed Jasmine Rice | D50: cat_side | E50: shop_curry | F50: 1 จาน | G50: 160 | H50: 10 | I50: 208 | J50: 4.3 | K50: 0.4 | L50: 46 | M50: 0 | N50: 0.6 | O50: 2 | P50: =TRUE() -> TRUE | Q50: 0 | R50: ข้าว|เครื่องเคียง|มังสวิรัติได้ | S50: images/menus/menu_049_thumb.webp | T50: images/menus/menu_049_detail.webp | U50: src_01 | V50: PENDING | W50: 2026-09-20

Sheet articles
A1: article_id | B1: title_th | C1: title_en | D1: topic | E1: summary | F1: key_points | G1: source_ids | H1: related_nutrient | I1: reading_minutes | J1: cover_image | K1: status | L1: published_at
A2: article_01 | B2: พลังงานที่ร่างกายต้องการต่อวันคำนวณอย่างไร | C2: How to Calculate Your Daily Energy Needs | D2: basic | E2: อธิบายความหมายของ BMR และ TDEE พร้อมวิธีคำนวณด้วยสมการ Mifflin-St Jeor | F2: BMR คือพลังงานที่ร่างกายใช้ขณะพักเพื่อรักษาการทำงานพื้นฐาน เช่น การหายใจและการเต้นของหัวใจ | สมการ Mifflin-St Jeor สำหรับเพศชาย BMR = 10 × น้ำหนัก (กก.) + 6.25 × ส่วนสูง (ซม.) − 5 × อายุ (ปี) + 5 ส่วนเพศหญิงใช้ −161 แทน +5 | TDEE คือ BMR คูณตัวคูณระดับกิจกรรม ตั้งแต่ 1.2 สำหรับผู้ที่นั่งทำงานเป็นหลัก ถึง 1.9 สำหรับผู้ใช้แรงงานหนัก | ตัวเลขที่ได้เป็นค่าประมาณเพื่อใช้วางแผน ไม่ใช่ค่าที่วัดได้จริงของแต่ละบุคคล | G2: src_05|src_02 | H2: energy_kcal | I2: 4 | J2: images/articles/article_01_cover.webp | K2: PUBLISHED | L2: 2026-09-20
A3: article_02 | B3: อ่านฉลากโภชนาการอย่างไรให้เป็น | C3: How to Read a Nutrition Label | D3: basic | E3: อธิบายหน่วยบริโภค ร้อยละของปริมาณที่แนะนำต่อวัน และฉลากหวาน มัน เค็ม | F3: ค่าบนฉลากโภชนาการเป็นค่าต่อหนึ่งหน่วยบริโภค ไม่ใช่ต่อทั้งบรรจุภัณฑ์ จึงต้องดูจำนวนหน่วยบริโภคต่อภาชนะประกอบทุกครั้ง | ร้อยละของปริมาณที่แนะนำต่อวันบอกว่าหนึ่งหน่วยบริโภคให้สารอาหารคิดเป็นสัดส่วนเท่าใดของความต้องการทั้งวัน | ฉลากหวาน มัน เค็ม ด้านหน้าบรรจุภัณฑ์แสดงพลังงาน น้ำตาล ไขมัน และโซเดียมของทั้งบรรจุภัณฑ์ ช่วยให้เปรียบเทียบสินค้าได้เร็ว | อาหารปรุงสำเร็จหน้าร้านไม่มีฉลาก ระบบนี้จึงแสดงค่าต่อหนึ่งจานแทน | G3: src_06 | H3: general | I3: 4 | J3: images/articles/article_02_cover.webp | K3: PUBLISHED | L3: 2026-09-20
A4: article_03 | B4: โซเดียมแฝงในอาหารจานเดียวของไทย | C4: Hidden Sodium in Thai Single-dish Meals | D4: sodium | E4: เปรียบเทียบปริมาณโซเดียมของเมนูยอดนิยมกับเกณฑ์ไม่เกิน 2,000 มิลลิกรัมต่อวัน | F4: องค์การอนามัยโลกแนะนำให้ผู้ใหญ่บริโภคโซเดียมไม่เกิน 2,000 มิลลิกรัมต่อวัน ซึ่งเทียบเท่าเกลือประมาณ 5 กรัม | กรมอนามัยรายงานว่าคนไทยได้รับโซเดียมเฉลี่ย 3,636 มิลลิกรัมต่อวัน เกือบสองเท่าของเกณฑ์ | โซเดียมส่วนใหญ่มาจากน้ำปลา ซีอิ๊ว ซอสปรุงรส ผงปรุงรส และน้ำซุป ก๋วยเตี๋ยวน้ำหนึ่งชามจึงอาจให้โซเดียมเกือบทั้งวัน | วิธีลดที่ทำได้ทันทีคือไม่ซดน้ำซุปจนหมด ชิมก่อนเติมเครื่องปรุง และสลับเมนูรสจัดกับผัดผักหรือแกงจืด | G4: src_03|src_16|src_01 | H4: sodium_mg | I4: 5 | J4: images/articles/article_03_cover.webp | K4: PUBLISHED | L4: 2026-09-20
A5: article_04 | B5: น้ำตาลในเครื่องดื่ม หนึ่งแก้วเท่ากับกี่ช้อนชา | C5: Sugar in Beverages | D5: sugar | E5: แปลงปริมาณน้ำตาลในเครื่องดื่มเป็นจำนวนช้อนชาเพื่อให้เห็นภาพ | F5: องค์การอนามัยโลกแนะนำให้ได้รับน้ำตาลอิสระน้อยกว่าร้อยละ 10 ของพลังงานทั้งวัน สำหรับผู้ที่ต้องการ 2,000 กิโลแคลอรีคือไม่เกินประมาณ 50 กรัม และจะดียิ่งขึ้นหากต่ำกว่าร้อยละ 5 | น้ำตาล 1 ช้อนชามีประมาณ 4 กรัม ชาไทยเย็นหนึ่งแก้วในระบบมีน้ำตาลประมาณ 44 กรัม หรือราว 11 ช้อนชา | การสั่งหวานน้อย หรือเปลี่ยนเป็นน้ำเปล่าและนมถั่วเหลืองสูตรหวานน้อย ช่วยลดน้ำตาลได้มากโดยไม่ต้องเปลี่ยนมื้ออาหาร | G5: src_04|src_01 | H5: sugar_g | I5: 4 | J5: images/articles/article_04_cover.webp | K5: PUBLISHED | L5: 2026-09-20
A6: article_05 | B6: โปรตีนพอหรือยังใน 1 วัน | C6: Are You Getting Enough Protein | D6: protein | E6: อธิบายการประมาณความต้องการโปรตีนจากน้ำหนักตัวและแหล่งโปรตีนราคาประหยัด | F6: ระบบใช้เป้าหมายโปรตีนประมาณ 1.0 กรัมต่อน้ำหนักตัว 1 กิโลกรัมต่อวันสำหรับผู้ใหญ่ทั่วไป | ไข่ เต้าหู้ นม และเนื้อไก่เป็นแหล่งโปรตีนที่ราคาไม่สูงและหาได้ทั่วไป | อาหารจานเดียวบางเมนูให้พลังงานสูงแต่โปรตีนต่ำ การเพิ่มไข่ต้มหรือเลือกเนื้อสัตว์ไม่ติดมันช่วยให้ได้โปรตีนครบง่ายขึ้น | G6: src_02 | H6: protein_g | I6: 3 | J6: images/articles/article_05_cover.webp | K6: PUBLISHED | L6: 2026-09-20
A7: article_06 | B7: ใยอาหารกับปัญหาผักน้อยในอาหารจานเดียว | C7: Dietary Fiber and Low-vegetable Meals | D7: fiber | E7: อธิบายบทบาทของใยอาหารและวิธีเพิ่มผักในเมนูสั่งประจำ | F7: ผู้ใหญ่ควรได้รับใยอาหารประมาณ 25 กรัมต่อวัน | อาหารจานเดียวส่วนใหญ่ในระบบมีใยอาหารเพียง 2 ถึง 4 กรัมต่อจาน จึงได้ใยอาหารไม่ถึงเกณฑ์แม้จะกินครบสามมื้อ | เพิ่มใยอาหารได้ด้วยการเลือกผัดผัก ส้มตำ หรือแกงส้ม และกินผลไม้เป็นของว่างแทนขนมหวาน | G7: src_02|src_07 | H7: fiber_g | I7: 4 | J7: images/articles/article_06_cover.webp | K7: PUBLISHED | L7: 2026-09-20
A8: article_07 | B8: ธงโภชนาการและการจัดจานแบบ 2:1:1 | C8: Thai Nutrition Flag and the 2:1:1 Plate | D8: basic | E8: อธิบายสัดส่วนผัก ข้าว และเนื้อสัตว์ในหนึ่งจานตามแนวทางของไทย | F8: ธงโภชนาการแนะนำให้กินข้าวและแป้งเป็นหลัก เพิ่มผักและผลไม้ และกินน้ำมัน น้ำตาล และเกลือแต่น้อย | จานสุขภาพ 2:1:1 คือแบ่งจานเป็น 4 ส่วน เป็นผัก 2 ส่วน ข้าวหรือแป้ง 1 ส่วน และเนื้อสัตว์หรือโปรตีน 1 ส่วน | อาหารจานเดียวส่วนใหญ่มีข้าวมากและผักน้อยกว่าที่แนะนำ ควรสั่งผักเพิ่มหรือกินผลไม้ร่วมด้วย | G8: src_07 | H8: carb_g | I8: 3 | J8: images/articles/article_07_cover.webp | K8: PUBLISHED | L8: 2026-09-20
A9: article_08 | B9: สั่งอาหารตามสั่งอย่างไรให้พลังงานไม่เกิน | C9: Ordering Made-to-order Food Wisely | D9: practice | E9: รวมเทคนิคการสั่งอาหาร เช่น ขอน้ำมันน้อย ขอผักเพิ่ม และเลี่ยงของทอด | F9: การขอน้ำมันน้อยและลดเครื่องปรุงช่วยลดทั้งพลังงานและโซเดียมโดยไม่ต้องเปลี่ยนเมนู | เลือกเมนูผัดที่มีผักเป็นส่วนประกอบหลัก และหลีกเลี่ยงการสั่งของทอดควบคู่กับข้าวผัดในมื้อเดียวกัน | ในระบบ ข้าวผัดอเมริกันให้พลังงาน 850 กิโลแคลอรี ขณะที่ข้าวผัดกะเพราไก่ให้ 580 กิโลแคลอรีในราคาที่ถูกกว่า | G9: src_01|src_07 | H9: energy_kcal | I9: 4 | J9: images/articles/article_08_cover.webp | K9: PUBLISHED | L9: 2026-09-20
A10: article_09 | B10: ไขมันอิ่มตัว ไขมันไม่อิ่มตัว และไขมันทรานส์ | C10: Types of Dietary Fat | D10: fat | E10: อธิบายชนิดของไขมันและผลต่อสุขภาพในระยะยาว | F10: ไขมันไม่อิ่มตัวพบในน้ำมันพืชส่วนใหญ่ ถั่ว และปลา ส่วนไขมันอิ่มตัวพบมากในไขมันสัตว์ หนังสัตว์ และกะทิ | ประเทศไทยห้ามผลิต นำเข้า หรือจำหน่ายน้ำมันที่ผ่านกระบวนการเติมไฮโดรเจนบางส่วน ซึ่งเป็นแหล่งหลักของไขมันทรานส์ ตามประกาศกระทรวงสาธารณสุข (ฉบับที่ 388) พ.ศ. 2561 | ข้าวหมูกรอบ คอหมูย่าง และข้าวขาหมูในระบบมีไขมันตั้งแต่ 28 กรัมต่อจานขึ้นไป ควรสลับกับเมนูที่ใช้เนื้อสัตว์ไม่ติดมัน | G10: src_02|src_17 | H10: fat_g | I10: 5 | J10: images/articles/article_09_cover.webp | K10: PUBLISHED | L10: 2026-09-20
A11: article_10 | B11: กินมังสวิรัติหรือเจอย่างไรให้ได้โปรตีนครบ | C11: Getting Enough Protein on a Plant-based Diet | D11: protein | E11: แนะนำแหล่งโปรตีนจากพืชและการจับคู่อาหารให้ได้กรดอะมิโนครบ | F11: แหล่งโปรตีนจากพืชที่หาง่าย ได้แก่ เต้าหู้ ถั่วเหลือง นมถั่วเหลือง และถั่วชนิดต่าง ๆ | การกินโปรตีนจากพืชหลายชนิดร่วมกัน เช่น ข้าวกับถั่ว ช่วยให้ได้กรดอะมิโนจำเป็นครบถ้วนขึ้น | ในระบบสามารถกรองเฉพาะเมนูที่เหมาะกับมังสวิรัติ และควรตรวจสอบว่าโปรตีนรวมทั้งวันถึงเป้าหมาย | G11: src_02 | H11: protein_g | I11: 3 | J11: images/articles/article_10_cover.webp | K11: PUBLISHED | L11: 2026-09-20
A12: article_11 | B12: งบจำกัดแต่อยากกินให้ครบ 5 หมู่ | C12: Eating Well on a Limited Budget | D12: practice | E12: แนะนำการจัดมื้ออาหารให้ครบหมู่ภายใต้งบประมาณต่อวันที่กำหนด | F12: เมนูที่ราคาใกล้เคียงกันอาจให้สารอาหารต่างกันมาก การเปรียบเทียบค่าต่อจานช่วยให้เลือกได้คุ้มขึ้น | ฟังก์ชันวางแผนมื้ออาหารให้ผู้ใช้กำหนดงบประมาณต่อวัน แล้วเลือกชุดเมนูที่พลังงานใกล้เป้าหมายและโซเดียมไม่เกินเกณฑ์ | น้ำเปล่าและผลไม้ตามฤดูกาลเป็นทางเลือกราคาไม่สูงที่ช่วยลดน้ำตาลจากเครื่องดื่มหวาน | G12: src_07|src_08 | H12: general | I12: 4 | J12: images/articles/article_11_cover.webp | K12: PUBLISHED | L12: 2026-09-20
A13: article_12 | B13: ข้อจำกัดของการประมาณค่าโภชนาการอาหารปรุงสำเร็จ | C13: Limitations of Estimating Nutrition in Cooked Dishes | D13: basic | E13: อธิบายว่าเหตุใดค่าโภชนาการของอาหารปรุงสำเร็จจึงเป็นค่าประมาณและมีความแปรปรวน | F13: ค่าในระบบเป็นค่าต่อหนึ่งหน่วยบริโภคตามน้ำหนักที่ระบุ แต่ละร้านใช้ปริมาณและเครื่องปรุงไม่เท่ากัน ค่าจริงจึงอาจสูงหรือต่ำกว่า | ค่าอ้างอิงมาจากฐานข้อมูลองค์ประกอบอาหารไทย หรือคำนวณจากวัตถุดิบตามสูตรมาตรฐานเมื่อไม่มีเมนูนั้นในฐานข้อมูล | ระบบนี้เป็นเครื่องมือให้ความรู้ ไม่ใช่คำแนะนำทางการแพทย์ ผู้มีโรคประจำตัวควรปรึกษาแพทย์หรือนักกำหนดอาหาร | G13: src_01|src_02 | H13: general | I13: 3 | J13: images/articles/article_12_cover.webp | K13: PUBLISHED | L13: 2026-09-20

Sheet menu_images
A1: image_id | B1: entity_id | C1: image_type | D1: file_thumb | E1: file_detail | F1: source_id | G1: license | H1: status
A2: img_0001 | B2: menu_001 | C2: menu | D2: menu_001_thumb.webp | E2: menu_001_detail.webp | F2: src_10 | G2: CC BY 4.0 | H2: DONE
A3: img_0002 | B3: menu_002 | C3: menu | D3: menu_002_thumb.webp | E3: menu_002_detail.webp | F3: src_10 | G3: CC BY-SA 3.0 | H3: DONE
A4: img_0003 | B4: menu_003 | C4: menu | D4: menu_003_thumb.webp | E4: menu_003_detail.webp | F4: src_10 | G4: CC BY-SA 4.0 | H4: DONE
A5: img_0004 | B5: menu_004 | C5: menu | D5: menu_004_thumb.webp | E5: menu_004_detail.webp | F5: src_10 | G5: CC0 | H5: DONE
A6: img_0005 | B6: menu_005 | C6: menu | D6: menu_005_thumb.webp | E6: menu_005_detail.webp | F6: src_10 | G6: CC0 | H6: DONE
A7: img_0006 | B7: menu_006 | C7: menu | D7: menu_006_thumb.webp | E7: menu_006_detail.webp | F7: src_10 | G7: CC0 | H7: DONE
A8: img_0007 | B8: menu_007 | C8: menu | D8: menu_007_thumb.webp | E8: menu_007_detail.webp | F8: src_10 | G8: CC0 | H8: DONE
A9: img_0008 | B9: menu_008 | C9: menu | D9: menu_008_thumb.webp | E9: menu_008_detail.webp | F9: src_10 | G9: CC0 | H9: DONE
A10: img_0009 | B10: menu_009 | C10: menu | D10: menu_009_thumb.webp | E10: menu_009_detail.webp | F10: src_10 | G10: CC BY-SA 3.0 | H10: DONE
A11: img_0010 | B11: menu_010 | C11: menu | D11: menu_010_thumb.webp | E11: menu_010_detail.webp | F11: src_10 | G11: CC BY 2.0 | H11: DONE
A12: img_0011 | B12: menu_011 | C12: menu | D12: menu_011_thumb.webp | E12: menu_011_detail.webp | F12: src_10 | G12: CC BY 2.0 | H12: DONE
... A50: img_0049 | B50: menu_049 | C50: menu | D50: menu_049_thumb.webp | E50: menu_049_detail.webp | F50: src_10 | G50: CC0 | H50: DONE
A51: img_0050 | B51: article_01 | C51: article_cover | D51: article_01_cover.webp | F51: src_09 | G51: Own Work | H51: TODO
A52: img_0051 | B52: article_02 | C52: article_cover | D52: article_02_cover.webp | F52: src_09 | G52: Own Work | H52: TODO
A53: img_0052 | B53: article_03 | C53: article_cover | D53: article_03_cover.webp | F53: src_09 | G53: Own Work | H53: TODO
A54: img_0053 | B54: article_04 | C54: article_cover | D54: article_04_cover.webp | F54: src_09 | G54: Own Work | H54: TODO
A55: img_0054 | B55: article_05 | C55: article_cover | D55: article_05_cover.webp | F55: src_09 | G55: Own Work | H55: TODO
A56: img_0055 | B56: article_06 | C56: article_cover | D56: article_06_cover.webp | F56: src_09 | G56: Own Work | H56: TODO
A57: img_0056 | B57: article_07 | C57: article_cover | D57: article_07_cover.webp | F57: src_09 | G57: Own Work | H57: TODO
A58: img_0057 | B58: article_08 | C58: article_cover | D58: article_08_cover.webp | F58: src_09 | G58: Own Work | H58: TODO
A59: img_0058 | B59: article_09 | C59: article_cover | D59: article_09_cover.webp | F59: src_09 | G59: Own Work | H59: TODO
A60: img_0059 | B60: article_10 | C60: article_cover | D60: article_10_cover.webp | F60: src_09 | G60: Own Work | H60: TODO
A61: img_0060 | B61: article_11 | C61: article_cover | D61: article_11_cover.webp | F61: src_09 | G61: Own Work | H61: TODO
A62: img_0061 | B62: article_12 | C62: article_cover | D62: article_12_cover.webp | F62: src_09 | G62: Own Work | H62: TODO

Sheet sources
A1: source_id | B1: source_name | C1: source_type | D1: url_reference | E1: owner_license | F1: used_for
A2: src_01 | B2: ฐานข้อมูลองค์ประกอบอาหารไทยออนไลน์ (Thai Food Composition Database 2015) | C2: primary | D2: https://inmu.mahidol.ac.th/thaifcd/ | E2: สถาบันโภชนาการ มหาวิทยาลัยมหิดล | F2: menus (ค่าโภชนาการ)
A3: src_02 | B3: ปริมาณสารอาหารอ้างอิงที่ควรได้รับประจำวันสำหรับคนไทย พ.ศ. 2563 (Dietary Reference Intake for Thais 2020) | C3: secondary | D3: สำนักโภชนาการ กรมอนามัย https://nutrition2.anamai.moph.go.th/th/dri/176096 | E3: เอกสารราชการ | F3: nutrient_limits, articles
A4: src_03 | B4: WHO guideline: Sodium intake for adults and children | C4: secondary | D4: https://www.who.int/publications/i/item/9789241504836 | E4: World Health Organization | F4: เกณฑ์โซเดียมไม่เกิน 2,000 มก./วัน
A5: src_04 | B5: WHO guideline: Sugars intake for adults and children | C5: secondary | D5: https://www.who.int/publications/i/item/9789241549028 | E5: World Health Organization | F5: เกณฑ์น้ำตาลอิสระไม่เกินร้อยละ 10
A6: src_05 | B6: Mifflin, M. D. et al. (1990). A new predictive equation for resting energy expenditure | C6: secondary | D6: The American Journal of Clinical Nutrition, 51(2), 241-247 | E6: วารสารวิชาการ | F6: สูตรคำนวณ BMR
A7: src_06 | B7: ประกาศกระทรวงสาธารณสุข (ฉบับที่ 445) พ.ศ. 2566 เรื่อง ฉลากโภชนาการ | C7: secondary | D7: สำนักงานคณะกรรมการอาหารและยา https://food.fda.moph.go.th/local-economy/category/local-economy-nutrition-label | E7: เอกสารราชการ | F7: บทความเรื่องฉลากโภชนาการ
A8: src_07 | B8: คู่มือธงโภชนาการ และแนวทางจานสุขภาพ 2:1:1 ของกรมอนามัย | C8: secondary | D8: สำนักโภชนาการ กรมอนามัย https://nutrition2.anamai.moph.go.th/th/book/201525 | E8: เอกสารราชการ | F8: บทความเรื่องการจัดจาน
A9: src_08 | B9: สำรวจราคาและเมนูจากร้านอาหารตามสั่งและโรงอาหาร | C9: primary | D9: สำรวจโดยผู้จัดทำ | E9: Own Work | F9: menus.price_thb, serving_desc
A10: src_09 | B10: ภาพปกบทความ ไอคอน ภาพประกอบ และโลโก้ โดยผู้จัดทำ | C10: primary | D10: ผู้จัดทำ | E10: Own Work | F10: menu_images (ภาพปกบทความ), icons, branding
A11: src_10 | B11: ภาพเมนูจากคลังภาพที่มีสัญญาอนุญาตเปิด: Wikimedia Commons (48 เมนู) และ Flickr (1 เมนู, menu_027) | C11: asset | D11: https://commons.wikimedia.org และ https://www.flickr.com (ลิงก์รายไฟล์ใน images/menus/image_credits.csv) | E11: CC0 / Public domain / CC BY / CC BY-SA / CC BY-NC-SA (ระบุรายไฟล์) | F11: menu_images (ภาพเมนู 98 ไฟล์)
A12: src_11 | B12: Lucide Icons (ใช้เป็นแนวทางการออกแบบ ไม่ได้คัดลอกไฟล์) | C12: asset | D12: https://lucide.dev | E12: ISC License | F12: อ้างอิงรูปแบบไอคอนเส้น 24x24 stroke 2
... A18: src_17 | B18: ประกาศกระทรวงสาธารณสุข (ฉบับที่ 388) พ.ศ. 2561 เรื่อง กำหนดอาหารที่ห้ามผลิต นำเข้า หรือจำหน่าย | C18: secondary | D18: https://food.fda.moph.go.th/food-law/388 | E18: สำนักงานคณะกรรมการอาหารและยา | F18: article_09 (ไขมันทรานส์)

Sheet users
A1: user_id | B1: role | C1: display_name | D1: email | E1: sex | F1: birth_year | G1: height_cm | H1: weight_kg | I1: activity_id | J1: goal_id | K1: budget_per_day_thb | L1: created_at
A2: user_001 | B2: member | C2: กิตติพัฒน์ | D2: user001@nutriplan.test | E2: male | F2: 2543 | G2: 181 | H2: 67 | I2: act_active | J2: goal_maintain | K2: 100 | L2: 2026-09-06
A3: user_002 | B3: member | C3: ปวีณา | D3: user002@nutriplan.test | E3: female | F3: 2548 | G3: 149 | H3: 49.3 | I3: act_light | J3: goal_gain | K3: 180 | L3: 2026-09-06
A4: user_003 | B4: member | C4: ธนากร | D4: user003@nutriplan.test | E4: male | F4: 2542 | G4: 166 | H4: 74.4 | I4: act_light | J4: goal_gain | K4: 200 | L4: 2026-09-06
A5: user_004 | B5: member | C5: สุภัสสรา | D5: user004@nutriplan.test | E5: female | F5: 2542 | G5: 156 | H5: 58 | I5: act_active | J5: goal_maintain | K5: 150 | L5: 2026-09-06
A6: user_005 | B6: member | C6: ชยพล | D6: user005@nutriplan.test | E6: male | F6: 2548 | G6: 182 | H6: 84.4 | I6: act_light | J6: goal_maintain | K6: 180 | L6: 2026-09-06
A7: user_006 | B7: member | C7: พิมพ์ชนก | D7: user006@nutriplan.test | E7: female | F7: 2548 | G7: 162 | H7: 46.8 | I7: act_moderate | J7: goal_maintain | K7: 100 | L7: 2026-09-06
A8: user_007 | B8: member | C8: วรเมธ | D8: user007@nutriplan.test | E8: male | F8: 2544 | G8: 168 | H8: 56.6 | I8: act_sedentary | J8: goal_lose | K8: 120 | L8: 2026-09-06
A9: user_008 | B9: member | C9: ศิริกัญญา | D9: user008@nutriplan.test | E9: female | F9: 2548 | G9: 151 | H9: 65.7 | I9: act_light | J9: goal_maintain | K9: 150 | L9: 2026-09-06
A10: user_009 | B10: member | C10: ภูริภัทร | D10: user009@nutriplan.test | E10: male | F10: 2548 | G10: 165 | H10: 58.8 | I10: act_active | J10: goal_lose | K10: 150 | L10: 2026-09-06
A11: user_010 | B11: member | C11: กมลชนก | D11: user010@nutriplan.test | E11: female | F11: 2549 | G11: 150 | H11: 60.9 | I11: act_moderate | J11: goal_lose | K11: 150 | L11: 2026-09-06
A12: user_011 | B12: member | C12: อนุชา | D12: user011@nutriplan.test | E12: male | F12: 2547 | G12: 179 | H12: 59.3 | I12: act_active | J12: goal_lose | K12: 200 | L12: 2026-09-06
A13: user_012 | B13: member | C13: ณัฐริกา | D13: user012@nutriplan.test | E13: female | F13: 2547 | G13: 153 | H13: 58.6 | I13: act_light | J13: goal_gain | K13: 150 | L13: 2026-09-06
... A26: user_025 | B26: admin | C26: ธนพร | D26: user025@nutriplan.test | E26: female | F26: 2545 | G26: 149 | H26: 57.2 | I26: act_sedentary | J26: goal_gain | K26: 180 | L26: 2026-09-06

Sheet user_targets
A1: user_id | B1: age_year | C1: bmr_kcal | D1: tdee_kcal | E1: target_kcal | F1: target_protein_g | G1: limit_sodium_mg | H1: limit_sugar_g | I1: target_fiber_g | J1: calculated_at | L1: หมายเหตุ
A2: =users!A2 -> user_001 | B2: =2569-users!F2 -> 26 | C2: =ROUND(10*users!H2+6.25*users!G2-5*B2+IF(users!E2="male",5,-161),0) -> 1676 | D2: =ROUND(C2*INDEX(activity_levels!$C$2:$C$6,MATCH(users!I2,activity_levels!$A$2:$A$6,0)),0) -> 2891 | E2: =D2+INDEX(health_goals!$C$2:$C$4,MATCH(users!J2,health_goals!$A$2:$A$4,0)) -> 2891 | F2: =ROUND(users!H2*1,0) -> 67 | G2: =INDEX(nutrient_limits!$F$2:$F$8,MATCH("sodium_mg",nutrient_limits!$A$2:$A$8,0)) -> 2000 | H2: =INDEX(nutrient_limits!$F$2:$F$8,MATCH("sugar_g",nutrient_limits!$A$2:$A$8,0)) -> 50 | I2: =INDEX(nutrient_limits!$F$2:$F$8,MATCH("fiber_g",nutrient_limits!$A$2:$A$8,0)) -> 25 | J2: 2026-09-20 | L2: ทุกคอลัมน์ยกเว้น calculated_at เป็นสูตร: age = 2569 − birth_year (ปี พ.ศ. ของวันที่คำนวณ), BMR ตามสมการ Mifflin-St Jeor (src_05), TDEE = BMR × pal_factor, target_kcal = TDEE + kcal_adjust, โปรตีน = น้ำหนัก × 1.0 ก./กก. (src_02), เพดานโซเดียม/น้ำตาล/ใยอาหารดึงจากชีต nutrient_limits
A3: =users!A3 -> user_002 | B3: =2569-users!F3 -> 21 | C3: =ROUND(10*users!H3+6.25*users!G3-5*B3+IF(users!E3="male",5,-161),0) -> 1158 | D3: =ROUND(C3*INDEX(activity_levels!$C$2:$C$6,MATCH(users!I3,activity_levels!$A$2:$A$6,0)),0) -> 1592 | E3: =D3+INDEX(health_goals!$C$2:$C$4,MATCH(users!J3,health_goals!$A$2:$A$4,0)) -> 1892 | F3: =ROUND(users!H3*1,0) -> 49 | G3: =INDEX(nutrient_limits!$F$2:$F$8,MATCH("sodium_mg",nutrient_limits!$A$2:$A$8,0)) -> 2000 | H3: =INDEX(nutrient_limits!$F$2:$F$8,MATCH("sugar_g",nutrient_limits!$A$2:$A$8,0)) -> 50 | I3: =INDEX(nutrient_limits!$F$2:$F$8,MATCH("fiber_g",nutrient_limits!$A$2:$A$8,0)) -> 25 | J3: 2026-09-20
A4: =users!A4 -> user_003 | B4: =2569-users!F4 -> 27 | C4: =ROUND(10*users!H4+6.25*users!G4-5*B4+IF(users!E4="male",5,-161),0) -> 1652 | D4: =ROUND(C4*INDEX(activity_levels!$C$2:$C$6,MATCH(users!I4,activity_levels!$A$2:$A$6,0)),0) -> 2272 | E4: =D4+INDEX(health_goals!$C$2:$C$4,MATCH(users!J4,health_goals!$A$2:$A$4,0)) -> 2572 | F4: =ROUND(users!H4*1,0) -> 74 | G4: =INDEX(nutrient_limits!$F$2:$F$8,MATCH("sodium_mg",nutrient_limits!$A$2:$A$8,0)) -> 2000 | H4: =INDEX(nutrient_limits!$F$2:$F$8,MATCH("sugar_g",nutrient_limits!$A$2:$A$8,0)) -> 50 | I4: =INDEX(nutrient_limits!$F$2:$F$8,MATCH("fiber_g",nutrient_limits!$A$2:$A$8,0)) -> 25 | J4: 2026-09-20
A5: =users!A5 -> user_004 | B5: =2569-users!F5 -> 27 | C5: =ROUND(10*users!H5+6.25*users!G5-5*B5+IF(users!E5="male",5,-161),0) -> 1259 | D5: =ROUND(C5*INDEX(activity_levels!$C$2:$C$6,MATCH(users!I5,activity_levels!$A$2:$A$6,0)),0) -> 2172 | E5: =D5+INDEX(health_goals!$C$2:$C$4,MATCH(users!J5,health_goals!$A$2:$A$4,0)) -> 2172 | F5: =ROUND(users!H5*1,0) -> 58 | G5: =INDEX(nutrient_limits!$F$2:$F$8,MATCH("sodium_mg",nutrient_limits!$A$2:$A$8,0)) -> 2000 | H5: =INDEX(nutrient_limits!$F$2:$F$8,MATCH("sugar_g",nutrient_limits!$A$2:$A$8,0)) -> 50 | I5: =INDEX(nutrient_limits!$F$2:$F$8,MATCH("fiber_g",nutrient_limits!$A$2:$A$8,0)) -> 25 | J5: 2026-09-20
A6: =users!A6 -> user_005 | B6: =2569-users!F6 -> 21 | C6: =ROUND(10*users!H6+6.25*users!G6-5*B6+IF(users!E6="male",5,-161),0) -> 1882 | D6: =ROUND(C6*INDEX(activity_levels!$C$2:$C$6,MATCH(users!I6,activity_levels!$A$2:$A$6,0)),0) -> 2588 | E6: =D6+INDEX(health_goals!$C$2:$C$4,MATCH(users!J6,health_goals!$A$2:$A$4,0)) -> 2588 | F6: =ROUND(users!H6*1,0) -> 84 | G6: =INDEX(nutrient_limits!$F$2:$F$8,MATCH("sodium_mg",nutrient_limits!$A$2:$A$8,0)) -> 2000 | H6: =INDEX(nutrient_limits!$F$2:$F$8,MATCH("sugar_g",nutrient_limits!$A$2:$A$8,0)) -> 50 | I6: =INDEX(nutrient_limits!$F$2:$F$8,MATCH("fiber_g",nutrient_limits!$A$2:$A$8,0)) -> 25 | J6: 2026-09-20
A7: =users!A7 -> user_006 | B7: =2569-users!F7 -> 21 | C7: =ROUND(10*users!H7+6.25*users!G7-5*B7+IF(users!E7="male",5,-161),0) -> 1215 | D7: =ROUND(C7*INDEX(activity_levels!$C$2:$C$6,MATCH(users!I7,activity_levels!$A$2:$A$6,0)),0) -> 1883 | E7: =D7+INDEX(health_goals!$C$2:$C$4,MATCH(users!J7,health_goals!$A$2:$A$4,0)) -> 1883 | F7: =ROUND(users!H7*1,0) -> 47 | G7: =INDEX(nutrient_limits!$F$2:$F$8,MATCH("sodium_mg",nutrient_limits!$A$2:$A$8,0)) -> 2000 | H7: =INDEX(nutrient_limits!$F$2:$F$8,MATCH("sugar_g",nutrient_limits!$A$2:$A$8,0)) -> 50 | I7: =INDEX(nutrient_limits!$F$2:$F$8,MATCH("fiber_g",nutrient_limits!$A$2:$A$8,0)) -> 25 | J7: 2026-09-20
A8: =users!A8 -> user_007 | B8: =2569-users!F8 -> 25 | C8: =ROUND(10*users!H8+6.25*users!G8-5*B8+IF(users!E8="male",5,-161),0) -> 1496 | D8: =ROUND(C8*INDEX(activity_levels!$C$2:$C$6,MATCH(users!I8,activity_levels!$A$2:$A$6,0)),0) -> 1795 | E8: =D8+INDEX(health_goals!$C$2:$C$4,MATCH(users!J8,health_goals!$A$2:$A$4,0)) -> 1295 | F8: =ROUND(users!H8*1,0) -> 57 | G8: =INDEX(nutrient_limits!$F$2:$F$8,MATCH("sodium_mg",nutrient_limits!$A$2:$A$8,0)) -> 2000 | H8: =INDEX(nutrient_limits!$F$2:$F$8,MATCH("sugar_g",nutrient_limits!$A$2:$A$8,0)) -> 50 | I8: =INDEX(nutrient_limits!$F$2:$F$8,MATCH("fiber_g",nutrient_limits!$A$2:$A$8,0)) -> 25 | J8: 2026-09-20
A9: =users!A9 -> user_008 | B9: =2569-users!F9 -> 21 | C9: =ROUND(10*users!H9+6.25*users!G9-5*B9+IF(users!E9="male",5,-161),0) -> 1335 | D9: =ROUND(C9*INDEX(activity_levels!$C$2:$C$6,MATCH(users!I9,activity_levels!$A$2:$A$6,0)),0) -> 1836 | E9: =D9+INDEX(health_goals!$C$2:$C$4,MATCH(users!J9,health_goals!$A$2:$A$4,0)) -> 1836 | F9: =ROUND(users!H9*1,0) -> 66 | G9: =INDEX(nutrient_limits!$F$2:$F$8,MATCH("sodium_mg",nutrient_limits!$A$2:$A$8,0)) -> 2000 | H9: =INDEX(nutrient_limits!$F$2:$F$8,MATCH("sugar_g",nutrient_limits!$A$2:$A$8,0)) -> 50 | I9: =INDEX(nutrient_limits!$F$2:$F$8,MATCH("fiber_g",nutrient_limits!$A$2:$A$8,0)) -> 25 | J9: 2026-09-20
A10: =users!A10 -> user_009 | B10: =2569-users!F10 -> 21 | C10: =ROUND(10*users!H10+6.25*users!G10-5*B10+IF(users!E10="male",5,-161),0) -> 1519 | D10: =ROUND(C10*INDEX(activity_levels!$C$2:$C$6,MATCH(users!I10,activity_levels!$A$2:$A$6,0)),0) -> 2620 | E10: =D10+INDEX(health_goals!$C$2:$C$4,MATCH(users!J10,health_goals!$A$2:$A$4,0)) -> 2120 | F10: =ROUND(users!H10*1,0) -> 59 | G10: =INDEX(nutrient_limits!$F$2:$F$8,MATCH("sodium_mg",nutrient_limits!$A$2:$A$8,0)) -> 2000 | H10: =INDEX(nutrient_limits!$F$2:$F$8,MATCH("sugar_g",nutrient_limits!$A$2:$A$8,0)) -> 50 | I10: =INDEX(nutrient_limits!$F$2:$F$8,MATCH("fiber_g",nutrient_limits!$A$2:$A$8,0)) -> 25 | J10: 2026-09-20
A11: =users!A11 -> user_010 | B11: =2569-users!F11 -> 20 | C11: =ROUND(10*users!H11+6.25*users!G11-5*B11+IF(users!E11="male",5,-161),0) -> 1286 | D11: =ROUND(C11*INDEX(activity_levels!$C$2:$C$6,MATCH(users!I11,activity_levels!$A$2:$A$6,0)),0) -> 1993 | E11: =D11+INDEX(health_goals!$C$2:$C$4,MATCH(users!J11,health_goals!$A$2:$A$4,0)) -> 1493 | F11: =ROUND(users!H11*1,0) -> 61 | G11: =INDEX(nutrient_limits!$F$2:$F$8,MATCH("sodium_mg",nutrient_limits!$A$2:$A$8,0)) -> 2000 | H11: =INDEX(nutrient_limits!$F$2:$F$8,MATCH("sugar_g",nutrient_limits!$A$2:$A$8,0)) -> 50 | I11: =INDEX(nutrient_limits!$F$2:$F$8,MATCH("fiber_g",nutrient_limits!$A$2:$A$8,0)) -> 25 | J11: 2026-09-20
A12: =users!A12 -> user_011 | B12: =2569-users!F12 -> 22 | C12: =ROUND(10*users!H12+6.25*users!G12-5*B12+IF(users!E12="male",5,-161),0) -> 1607 | D12: =ROUND(C12*INDEX(activity_levels!$C$2:$C$6,MATCH(users!I12,activity_levels!$A$2:$A$6,0)),0) -> 2772 | E12: =D12+INDEX(health_goals!$C$2:$C$4,MATCH(users!J12,health_goals!$A$2:$A$4,0)) -> 2272 | F12: =ROUND(users!H12*1,0) -> 59 | G12: =INDEX(nutrient_limits!$F$2:$F$8,MATCH("sodium_mg",nutrient_limits!$A$2:$A$8,0)) -> 2000 | H12: =INDEX(nutrient_limits!$F$2:$F$8,MATCH("sugar_g",nutrient_limits!$A$2:$A$8,0)) -> 50 | I12: =INDEX(nutrient_limits!$F$2:$F$8,MATCH("fiber_g",nutrient_limits!$A$2:$A$8,0)) -> 25 | J12: 2026-09-20
A13: =users!A13 -> user_012 | B13: =2569-users!F13 -> 22 | C13: =ROUND(10*users!H13+6.25*users!G13-5*B13+IF(users!E13="male",5,-161),0) -> 1271 | D13: =ROUND(C13*INDEX(activity_levels!$C$2:$C$6,MATCH(users!I13,activity_levels!$A$2:$A$6,0)),0) -> 1748 | E13: =D13+INDEX(health_goals!$C$2:$C$4,MATCH(users!J13,health_goals!$A$2:$A$4,0)) -> 2048 | F13: =ROUND(users!H13*1,0) -> 59 | G13: =INDEX(nutrient_limits!$F$2:$F$8,MATCH("sodium_mg",nutrient_limits!$A$2:$A$8,0)) -> 2000 | H13: =INDEX(nutrient_limits!$F$2:$F$8,MATCH("sugar_g",nutrient_limits!$A$2:$A$8,0)) -> 50 | I13: =INDEX(nutrient_limits!$F$2:$F$8,MATCH("fiber_g",nutrient_limits!$A$2:$A$8,0)) -> 25 | J13: 2026-09-20
A14: =users!A14 -> user_013 | B14: =2569-users!F14 -> 21 | C14: =ROUND(10*users!H14+6.25*users!G14-5*B14+IF(users!E14="male",5,-161),0) -> 1807 | D14: =ROUND(C14*INDEX(activity_levels!$C$2:$C$6,MATCH(users!I14,activity_levels!$A$2:$A$6,0)),0) -> 2485 | E14: =D14+INDEX(health_goals!$C$2:$C$4,MATCH(users!J14,health_goals!$A$2:$A$4,0)) -> 2785 | F14: =ROUND(users!H14*1,0) -> 85 | G14: =INDEX(nutrient_limits!$F$2:$F$8,MATCH("sodium_mg",nutrient_limits!$A$2:$A$8,0)) -> 2000 | H14: =INDEX(nutrient_limits!$F$2:$F$8,MATCH("sugar_g",nutrient_limits!$A$2:$A$8,0)) -> 50 | I14: =INDEX(nutrient_limits!$F$2:$F$8,MATCH("fiber_g",nutrient_limits!$A$2:$A$8,0)) -> 25 | J14: 2026-09-20
... A26: =users!A26 -> user_025 | B26: =2569-users!F26 -> 24 | C26: =ROUND(10*users!H26+6.25*users!G26-5*B26+IF(users!E26="male",5,-161),0) -> 1222 | D26: =ROUND(C26*INDEX(activity_levels!$C$2:$C$6,MATCH(users!I26,activity_levels!$A$2:$A$6,0)),0) -> 1466 | E26: =D26+INDEX(health_goals!$C$2:$C$4,MATCH(users!J26,health_goals!$A$2:$A$4,0)) -> 1766 | F26: =ROUND(users!H26*1,0) -> 57 | G26: =INDEX(nutrient_limits!$F$2:$F$8,MATCH("sodium_mg",nutrient_limits!$A$2:$A$8,0)) -> 2000 | H26: =INDEX(nutrient_limits!$F$2:$F$8,MATCH("sugar_g",nutrient_limits!$A$2:$A$8,0)) -> 50 | I26: =INDEX(nutrient_limits!$F$2:$F$8,MATCH("fiber_g",nutrient_limits!$A$2:$A$8,0)) -> 25 | J26: 2026-09-20

Sheet meal_logs
A1: log_id | B1: user_id | C1: log_date | D1: meal_type | E1: menu_id | F1: qty | G1: logged_at
A2: log_0001 | B2: user_001 | C2: 2026-09-08 | D2: breakfast | E2: menu_016 | F2: 1 | G2: 2026-09-08T07:45:00+07:00
A3: log_0002 | B3: user_001 | C3: 2026-09-08 | D3: lunch | E3: menu_018 | F3: 1 | G3: 2026-09-08T12:10:00+07:00
A4: log_0003 | B4: user_001 | C4: 2026-09-08 | D4: dinner | E4: menu_035 | F4: 1 | G4: 2026-09-08T18:30:00+07:00
A5: log_0004 | B5: user_001 | C5: 2026-09-08 | D5: snack | E5: menu_046 | F5: 1 | G5: 2026-09-08T15:20:00+07:00
A6: log_0005 | B6: user_001 | C6: 2026-09-08 | D6: dinner | E6: menu_032 | F6: 1 | G6: 2026-09-08T18:30:00+07:00
A7: log_0006 | B7: user_001 | C7: 2026-09-09 | D7: breakfast | E7: menu_024 | F7: 1 | G7: 2026-09-09T07:45:00+07:00
A8: log_0007 | B8: user_001 | C8: 2026-09-09 | D8: lunch | E8: menu_018 | F8: 1 | G8: 2026-09-09T12:10:00+07:00
A9: log_0008 | B9: user_001 | C9: 2026-09-09 | D9: dinner | E9: menu_032 | F9: 1 | G9: 2026-09-09T18:30:00+07:00
A10: log_0009 | B10: user_001 | C10: 2026-09-10 | D10: breakfast | E10: menu_003 | F10: 1 | G10: 2026-09-10T07:45:00+07:00
A11: log_0010 | B11: user_001 | C11: 2026-09-10 | D11: lunch | E11: menu_019 | F11: 1 | G11: 2026-09-10T12:10:00+07:00
A12: log_0011 | B12: user_001 | C12: 2026-09-10 | D12: dinner | E12: menu_001 | F12: 1 | G12: 2026-09-10T18:30:00+07:00
A13: log_0012 | B13: user_001 | C13: 2026-09-11 | D13: breakfast | E13: menu_024 | F13: 1 | G13: 2026-09-11T07:45:00+07:00
... A1109: log_1108 | B1109: user_025 | C1109: 2026-09-20 | D1109: snack | E1109: menu_043 | F1109: 1 | G1109: 2026-09-20T15:20:00+07:00
